setup.py
rbt_github/__init__.py
rbt_github/command.py
rbt_github.egg-info/PKG-INFO
rbt_github.egg-info/SOURCES.txt
rbt_github.egg-info/dependency_links.txt
rbt_github.egg-info/entry_points.txt
rbt_github.egg-info/requires.txt
rbt_github.egg-info/top_level.txt