Metadata-Version: 1.0
Name: rbt-github
Version: 0.2.0
Summary: Reviewboard github extension
Home-page: http://github.com/jfarrell
Author: Jake Farrell
Author-email: jfarrell@apache.org
License: Apache v2
Platform: UNKNOWN
Classifier: Environment :: Console
Classifier: Intended Audience :: Developers
Classifier: Operating System :: OS Independent
Classifier: Programming Language :: Python
Classifier: Topic :: Software Development
